dateiter/__init__.py
dateiter/__main__.py
dateiter/py.typed
dateiter-1.2.1.dist-info/METADATA
dateiter-1.2.1.dist-info/WHEEL
dateiter-1.2.1.dist-info/entry_points.txt
dateiter-1.2.1.dist-info/RECORD
