Metadata-Version: 2.1
Name: dateiter
Version: 1.2.1
Summary: 
Author: yassun7010
Author-email: yassun7010@outlook.com
Requires-Python: >=3.11,<4.0
Classifier: Programming Language :: Python :: 3
Classifier: Programming Language :: Python :: 3.11
Classifier: Programming Language :: Python :: 3.12
